{"format":"linked-data-api","version":"0.2","result":{"_about":"http:\/\/reference.data.gov.uk\/2011-09-30\/doc\/public-body\/monitor.json","definition":"http:\/\/organogram.data.gov.uk\/api#publicBody","extendedMetadataVersion":"http:\/\/reference.data.gov.uk\/2011-09-30\/doc\/public-body\/monitor.json?_metadata=all%2Cviews%2Cformats%2Cexecution%2Cbindings","primaryTopic":{"_about":"http:\/\/reference.data.gov.uk\/id\/public-body\/monitor","parentDepartment":{"_about":"http:\/\/reference.data.gov.uk\/id\/department\/dh","label":["Department of Health"]},"type":["http:\/\/www.w3.org\/ns\/org#Organization","http:\/\/reference.data.gov.uk\/def\/central-government\/PublicBody"],"label":["Monitor"],"unit":[{"_about":"http:\/\/reference.data.gov.uk\/id\/public-body\/monitor\/unit\/executive-office","label":["Executive office"]},{"_about":"http:\/\/reference.data.gov.uk\/id\/public-body\/monitor\/unit\/communications-public-affairs-team","label":["Communications & Public Affairs Team"]},{"_about":"http:\/\/reference.data.gov.uk\/id\/public-body\/monitor\/unit\/legislative-support-and-policy-research-workstream","label":["Legislative Support and Policy Research Workstream"]},{"_about":"http:\/\/reference.data.gov.uk\/id\/public-body\/monitor\/unit\/licensing-workstream","label":["Licensing Workstream"]},{"_about":"http:\/\/reference.data.gov.uk\/id\/public-body\/monitor\/unit\/competition-workstream","label":["Competition Workstream"]},{"_about":"http:\/\/reference.data.gov.uk\/id\/public-body\/monitor\/unit\/build-workstream","label":["Build Workstream"]},{"_about":"http:\/\/reference.data.gov.uk\/id\/public-body\/monitor\/unit\/regulatory-operations-directorate","label":["Regulatory Operations Directorate"]},{"_about":"http:\/\/reference.data.gov.uk\/id\/public-body\/monitor\/unit\/legal-services-directorate","label":["Legal Services Directorate"]},{"_about":"http:\/\/reference.data.gov.uk\/id\/public-body\/monitor\/unit\/strategy-directorate","label":["Strategy Directorate"]},{"_about":"http:\/\/reference.data.gov.uk\/id\/public-body\/monitor\/unit\/programme-management-office","label":["Programme Management Office"]},{"_about":"http:\/\/reference.data.gov.uk\/id\/public-body\/monitor\/unit\/human-resources-corporate-services-directorate","label":["Human Resources & Corporate Services Directorate"]},{"_about":"http:\/\/reference.data.gov.uk\/id\/public-body\/monitor\/unit\/pricing-workstream","label":["Pricing Workstream"]},{"_about":"http:\/\/reference.data.gov.uk\/id\/public-body\/monitor\/unit\/continuity-of-service-workstream","label":["Continuity of Service Workstream"]}],"primaryTopicOf":["http:\/\/reference.data.gov.uk\/2011-09-30\/doc\/public-body\/monitor.json"]}}}